captcha/__init__.py
captcha/audio.py
captcha/image.py
captcha/py.typed
captcha/data/DroidSansMono.ttf
captcha/data/beep.wav
captcha/data/ /default.wav
captcha/data/!/default.wav
"captcha/data/""/default.wav"
captcha/data/#/default.wav
captcha/data/$/default.wav
captcha/data/%/default.wav
captcha/data/&/default.wav
captcha/data/'/default.wav
captcha/data/(/default.wav
captcha/data/)/default.wav
captcha/data/*/default.wav
captcha/data/+/default.wav
"captcha/data/,/default.wav"
captcha/data/-/default.wav
captcha/data/0/default.wav
captcha/data/1/default.wav
captcha/data/2/default.wav
captcha/data/3/default.wav
captcha/data/4/default.wav
captcha/data/5/default.wav
captcha/data/6/default.wav
captcha/data/7/default.wav
captcha/data/8/default.wav
captcha/data/9/default.wav
captcha/data/:/default.wav
captcha/data/;/default.wav
captcha/data/</default.wav
captcha/data/=/default.wav
captcha/data/>/default.wav
captcha/data/?/default.wav
captcha/data/@/default.wav
captcha/data/A/default.wav
captcha/data/B/default.wav
captcha/data/C/default.wav
captcha/data/D/default.wav
captcha/data/E/default.wav
captcha/data/F/default.wav
captcha/data/G/default.wav
captcha/data/H/default.wav
captcha/data/I/default.wav
captcha/data/J/default.wav
captcha/data/K/default.wav
captcha/data/L/default.wav
captcha/data/M/default.wav
captcha/data/N/default.wav
captcha/data/O/default.wav
captcha/data/P/default.wav
captcha/data/Q/default.wav
captcha/data/R/default.wav
captcha/data/S/default.wav
captcha/data/T/default.wav
captcha/data/U/default.wav
captcha/data/V/default.wav
captcha/data/W/default.wav
captcha/data/X/default.wav
captcha/data/Y/default.wav
captcha/data/Z/default.wav
captcha/data/[/default.wav
captcha/data/]/default.wav
captcha/data/^/default.wav
captcha/data/_/default.wav
captcha/data/`/default.wav
captcha/data/a/default.wav
captcha/data/b/default.wav
captcha/data/c/default.wav
captcha/data/d/default.wav
captcha/data/e/default.wav
captcha/data/f/default.wav
captcha/data/g/default.wav
more_captcha-1.1.0.dist-info/LICENSE
more_captcha-1.1.0.dist-info/METADATA
more_captcha-1.1.0.dist-info/WHEEL
more_captcha-1.1.0.dist-info/top_level.txt
more_captcha-1.1.0.dist-info/RECORD
