Metadata-Version: 2.1
Name: more-captcha
Version: 1.1.0
Summary: A captcha library that generates audio and image CAPTCHAs.
Author-email: Hsiaoming Yang <me@lepture.com>, Ari Archer <ari@ari.lt>
License: BSD-3-Clause
Project-URL: Documentation, https://captcha.lepture.com/
Project-URL: Source, https://ari.lt/gh/captcha
Project-URL: Original, https://github.com/lepture/captcha
Classifier: Development Status :: 6 - Mature
Classifier: Environment :: Console
Classifier: Environment :: Web Environment
Classifier: Intended Audience :: Developers
Classifier: License :: OSI Approved :: BSD License
Classifier: Operating System :: OS Independent
Classifier: Programming Language :: Python
Classifier: Programming Language :: Python :: 3
Classifier: Programming Language :: Python :: 3.8
Classifier: Programming Language :: Python :: 3.9
Classifier: Programming Language :: Python :: 3.10
Classifier: Programming Language :: Python :: 3.11
Classifier: Programming Language :: Python :: 3.12
Classifier: Programming Language :: Python :: 3.13
Classifier: Programming Language :: Python :: Implementation :: CPython
Classifier: Topic :: Security
Requires-Python: >=3.8
License-File: LICENSE
Requires-Dist: Pillow
